github/com/gogo/protobuf/gogoproto/gogo_pb2.py
github/com/gogo/protobuf/gogoproto/gogo_pb2_grpc.py
github/com/kubernetes/kubelet/pkg/apis/podresources/v1/api_pb2.py
github/com/kubernetes/kubelet/pkg/apis/podresources/v1/api_pb2_grpc.py
rocm_smi_exporter/__init__.py
rocm_smi_exporter/kubelet.py
rocm_smi_exporter/main.py
rocm_smi_exporter/metrics.py
rocm_smi_exporter/rocm_smi.py
rocm_smi_exporter/rsmiBindings.py
rocm_smi_exporter/wrapper.py
rocm_smi_exporter-0.0.1a14.dist-info/METADATA
rocm_smi_exporter-0.0.1a14.dist-info/WHEEL
rocm_smi_exporter-0.0.1a14.dist-info/entry_points.txt
rocm_smi_exporter-0.0.1a14.dist-info/top_level.txt
rocm_smi_exporter-0.0.1a14.dist-info/RECORD
