Metadata-Version: 2.1
Name: rocm-smi-exporter
Version: 0.0.1a14
Summary: Export rocm-smi metrics as prometheus metrics
Author-email: Yaxiong Zhao <yaxiong@powerml.co>
Maintainer-email: Yaxiong Zhao <yaxiong@powerml.co>
Requires-Python: >=3.8
Requires-Dist: prometheus-client ==0.20.0
Requires-Dist: pyrsmi ==1.0.1
Requires-Dist: grpcio ==1.66.0
Requires-Dist: protobuf ==5.27.3
